src/add_and_multiple/__init__.py
src/add_and_multiple/add_multiple.py
test/add.py
test/multiple.py
add_and_multiple-0.0.1.dist-info/METADATA
add_and_multiple-0.0.1.dist-info/WHEEL
add_and_multiple-0.0.1.dist-info/top_level.txt
add_and_multiple-0.0.1.dist-info/RECORD
